aind_data_transfer_service/__init__.py
aind_data_transfer_service/log_handler.py
aind_data_transfer_service/server.py
aind_data_transfer_service/configs/__init__.py
aind_data_transfer_service/configs/csv_handler.py
aind_data_transfer_service/configs/job_upload_template.py
aind_data_transfer_service/configs/platforms_v1.py
aind_data_transfer_service/models/__init__.py
aind_data_transfer_service/models/core.py
aind_data_transfer_service/models/internal.py
aind_data_transfer_service-2.0.0.dist-info/licenses/LICENSE
aind_data_transfer_service-2.0.0.dist-info/METADATA
aind_data_transfer_service-2.0.0.dist-info/WHEEL
aind_data_transfer_service-2.0.0.dist-info/top_level.txt
aind_data_transfer_service-2.0.0.dist-info/RECORD
