Metadata-Version: 2.4
Name: aind-data-transfer-service
Version: 2.0.0
Summary: Service that handles requests to upload data to the cloud
Author: Allen Institute for Neural Dynamics
License: MIT
Classifier: Programming Language :: Python :: 3
Requires-Python: >=3.10
License-File: LICENSE
Requires-Dist: aind-data-schema-models>=0.3.2
Requires-Dist: email-validator
Requires-Dist: pydantic>=2.0
Requires-Dist: pydantic-settings>=2.0
Provides-Extra: dev
Requires-Dist: aind-data-transfer-service[server]; extra == "dev"
Requires-Dist: black; extra == "dev"
Requires-Dist: coverage; extra == "dev"
Requires-Dist: flake8; extra == "dev"
Requires-Dist: interrogate; extra == "dev"
Requires-Dist: isort; extra == "dev"
Provides-Extra: docs
Requires-Dist: Sphinx; extra == "docs"
Requires-Dist: furo; extra == "docs"
Provides-Extra: server
Requires-Dist: aind-data-schema==2.0.0; extra == "server"
Requires-Dist: boto3; extra == "server"
Requires-Dist: boto3-stubs[ssm]; extra == "server"
Requires-Dist: fastapi>=0.115.13; extra == "server"
Requires-Dist: httpx; extra == "server"
Requires-Dist: jinja2; extra == "server"
Requires-Dist: starlette<0.47.0,>=0.40.0; extra == "server"
Requires-Dist: starlette_wtf; extra == "server"
Requires-Dist: uvicorn[standard]; extra == "server"
Requires-Dist: wtforms; extra == "server"
Requires-Dist: requests==2.25.0; extra == "server"
Requires-Dist: openpyxl; extra == "server"
Requires-Dist: python-logging-loki; extra == "server"
Requires-Dist: authlib; extra == "server"
Dynamic: license-file
